[
  {
    "uuid": "d22bc87e-1c3e-485a-aff3-e0f2734c0336",
    "tool": "selenium",
    "name": "Login Test",
    "fullName": "com.example.selenium.tests.DemoTests.Login Test",
    "status": "passed",
    "stage": "finished",
    "start": 1779082362883,
    "stop": 1779082367883,
    "duration": 5000,
    "steps": [
      {
        "name": "🌐 Navigate to login page",
        "status": "passed",
        "start": 1779082362883,
        "stop": 1779082362983,
        "duration": 100,
        "steps": [
          {
            "name": "📤 Action Details",
            "status": "passed",
            "start": 1778513543000,
            "stop": 1778513543050,
            "duration": 50,
            "steps": [
              {
                "name": "Type: GET",
                "status": "passed",
                "start": 1778513543000,
                "stop": 1778513543020,
                "duration": 20
              },
              {
                "name": "URL: Navigate to login page",
                "status": "passed",
                "start": 1778513543020,
                "stop": 1778513543050,
                "duration": 30
              }
            ]
          },
          {
            "name": "✅ Result",
            "status": "passed",
            "start": 1778513543050,
            "stop": 1778513543100,
            "duration": 50,
            "statusDetails": {
              "message": "Status: passed | Duration: ~100ms"
            }
          }
        ]
      },
      {
        "name": "⌨️ Enter credentials",
        "status": "passed",
        "start": 1779082363883,
        "stop": 1779082363983,
        "duration": 100,
        "steps": [
          {
            "name": "🎯 Element Details",
            "status": "passed",
            "start": 1778513544000,
            "stop": 1778513544050,
            "duration": 50,
            "steps": [
              {
                "name": "Locator: Enter credentials",
                "status": "passed",
                "start": 1778513544000,
                "stop": 1778513544025,
                "duration": 25
              },
              {
                "name": "Value: N/A",
                "status": "passed",
                "start": 1778513544025,
                "stop": 1778513544050,
                "duration": 25
              }
            ]
          },
          {
            "name": "✅ Result",
            "status": "passed",
            "start": 1778513544050,
            "stop": 1778513544080,
            "duration": 30,
            "statusDetails": {
              "message": "Status: passed | Duration: ~80ms"
            }
          }
        ]
      },
      {
        "name": "🖱️ Click login button",
        "status": "passed",
        "start": 1779082364383,
        "stop": 1779082364483,
        "duration": 100,
        "steps": [
          {
            "name": "🎯 Element Details",
            "status": "passed",
            "start": 1778513544500,
            "stop": 1778513544530,
            "duration": 30,
            "steps": [
              {
                "name": "Locator: Click login button",
                "status": "passed",
                "start": 1778513544500,
                "stop": 1778513544515,
                "duration": 15
              },
              {
                "name": "Action: Click",
                "status": "passed",
                "start": 1778513544515,
                "stop": 1778513544530,
                "duration": 15
              }
            ]
          },
          {
            "name": "✅ Result",
            "status": "passed",
            "start": 1778513544530,
            "stop": 1778513544550,
            "duration": 20,
            "statusDetails": {
              "message": "Status: passed | Duration: ~50ms"
            }
          }
        ]
      }
    ],
    "attachments": [],
    "extra": {
      "selenium": {
        "retries": 0,
        "browser": {
          "name": "chrome",
          "version": "120.0",
          "platform": "Windows 10"
        }
      },
      "parameters": [],
      "testClass": "com.example.selenium.tests.DemoTests",
      "testMethod": "Login Test"
    }
  },
  {
    "uuid": "e4e8eebf-f589-4097-b787-058e1aacb545",
    "tool": "selenium",
    "name": "Search Functionality Test",
    "fullName": "com.example.selenium.tests.DemoTests.Search Functionality Test",
    "status": "passed",
    "stage": "finished",
    "start": 1779082367883,
    "stop": 1779082371883,
    "duration": 4000,
    "steps": [
      {
        "name": "📌 Open search page",
        "status": "passed",
        "start": 1779082367883,
        "stop": 1779082367983,
        "duration": 100,
        "steps": []
      },
      {
        "name": "⌨️ Enter search term",
        "status": "passed",
        "start": 1779082368683,
        "stop": 1779082368783,
        "duration": 100,
        "steps": [
          {
            "name": "🎯 Element Details",
            "status": "passed",
            "start": 1778513548800,
            "stop": 1778513548850,
            "duration": 50,
            "steps": [
              {
                "name": "Locator: Enter search term",
                "status": "passed",
                "start": 1778513548800,
                "stop": 1778513548825,
                "duration": 25
              },
              {
                "name": "Value: N/A",
                "status": "passed",
                "start": 1778513548825,
                "stop": 1778513548850,
                "duration": 25
              }
            ]
          },
          {
            "name": "✅ Result",
            "status": "passed",
            "start": 1778513548850,
            "stop": 1778513548880,
            "duration": 30,
            "statusDetails": {
              "message": "Status: passed | Duration: ~80ms"
            }
          }
        ]
      },
      {
        "name": "📌 Verify results",
        "status": "passed",
        "start": 1779082369283,
        "stop": 1779082369383,
        "duration": 100,
        "steps": []
      }
    ],
    "attachments": [],
    "extra": {
      "selenium": {
        "retries": 0,
        "browser": {
          "name": "chrome",
          "version": "120.0",
          "platform": "Windows 10"
        }
      },
      "parameters": [],
      "testClass": "com.example.selenium.tests.DemoTests",
      "testMethod": "Search Functionality Test"
    }
  },
  {
    "uuid": "4195d8f8-0ef6-4bbc-b049-cdf54f6d72a9",
    "tool": "selenium",
    "name": "Add to Cart Test",
    "fullName": "com.example.selenium.tests.DemoTests.Add to Cart Test",
    "status": "passed",
    "stage": "finished",
    "start": 1779082371883,
    "stop": 1779082375383,
    "duration": 3500,
    "steps": [
      {
        "name": "📌 Select product",
        "status": "passed",
        "start": 1779082371883,
        "stop": 1779082371983,
        "duration": 100,
        "steps": []
      },
      {
        "name": "🖱️ Click add to cart",
        "status": "passed",
        "start": 1779082372883,
        "stop": 1779082372983,
        "duration": 100,
        "steps": [
          {
            "name": "🎯 Element Details",
            "status": "passed",
            "start": 1778513553000,
            "stop": 1778513553030,
            "duration": 30,
            "steps": [
              {
                "name": "Locator: Click add to cart",
                "status": "passed",
                "start": 1778513553000,
                "stop": 1778513553015,
                "duration": 15
              },
              {
                "name": "Action: Click",
                "status": "passed",
                "start": 1778513553015,
                "stop": 1778513553030,
                "duration": 15
              }
            ]
          },
          {
            "name": "✅ Result",
            "status": "passed",
            "start": 1778513553030,
            "stop": 1778513553050,
            "duration": 20,
            "statusDetails": {
              "message": "Status: passed | Duration: ~50ms"
            }
          }
        ]
      }
    ],
    "attachments": [],
    "extra": {
      "selenium": {
        "retries": 0,
        "browser": {
          "name": "chrome",
          "version": "120.0",
          "platform": "Windows 10"
        }
      },
      "parameters": [],
      "testClass": "com.example.selenium.tests.DemoTests",
      "testMethod": "Add to Cart Test"
    }
  },
  {
    "uuid": "f0ecb4ee-e3fe-49ed-a107-633d265b7461",
    "tool": "selenium",
    "name": "Checkout Process Test",
    "fullName": "com.example.selenium.tests.DemoTests.Checkout Process Test",
    "status": "flaky",
    "stage": "finished",
    "start": 1779082375383,
    "stop": 1779082381383,
    "duration": 6000,
    "steps": [
      {
        "name": "📌 Go to cart",
        "status": "passed",
        "start": 1779082375383,
        "stop": 1779082375483,
        "duration": 100,
        "steps": []
      },
      {
        "name": "⌨️ Enter shipping details",
        "status": "passed",
        "start": 1779082376583,
        "stop": 1779082376683,
        "duration": 100,
        "steps": [
          {
            "name": "🎯 Element Details",
            "status": "passed",
            "start": 1778513556700,
            "stop": 1778513556750,
            "duration": 50,
            "steps": [
              {
                "name": "Locator: Enter shipping details",
                "status": "passed",
                "start": 1778513556700,
                "stop": 1778513556725,
                "duration": 25
              },
              {
                "name": "Value: N/A",
                "status": "passed",
                "start": 1778513556725,
                "stop": 1778513556750,
                "duration": 25
              }
            ]
          },
          {
            "name": "✅ Result",
            "status": "passed",
            "start": 1778513556750,
            "stop": 1778513556780,
            "duration": 30,
            "statusDetails": {
              "message": "Status: passed | Duration: ~80ms"
            }
          }
        ]
      },
      {
        "name": "📌 Complete payment",
        "status": "passed",
        "start": 1779082378083,
        "stop": 1779082378183,
        "duration": 100,
        "steps": []
      }
    ],
    "attachments": [],
    "extra": {
      "selenium": {
        "retries": 1,
        "browser": {
          "name": "chrome",
          "version": "120.0",
          "platform": "Windows 10"
        }
      },
      "parameters": [],
      "testClass": "com.example.selenium.tests.DemoTests",
      "testMethod": "Checkout Process Test",
      "flakyReason": "Test passed after retry"
    }
  },
  {
    "uuid": "ac8526ee-e106-4968-96e7-dc20e953fcb5",
    "tool": "selenium",
    "name": "User Profile Test",
    "fullName": "com.example.selenium.tests.DemoTests.User Profile Test",
    "status": "passed",
    "stage": "finished",
    "start": 1779082381383,
    "stop": 1779082385883,
    "duration": 4500,
    "steps": [
      {
        "name": "🌐 Navigate to profile",
        "status": "passed",
        "start": 1779082381383,
        "stop": 1779082381483,
        "duration": 100,
        "steps": [
          {
            "name": "📤 Action Details",
            "status": "passed",
            "start": 1778513561500,
            "stop": 1778513561550,
            "duration": 50,
            "steps": [
              {
                "name": "Type: GET",
                "status": "passed",
                "start": 1778513561500,
                "stop": 1778513561520,
                "duration": 20
              },
              {
                "name": "URL: Navigate to profile",
                "status": "passed",
                "start": 1778513561520,
                "stop": 1778513561550,
                "duration": 30
              }
            ]
          },
          {
            "name": "✅ Result",
            "status": "passed",
            "start": 1778513561550,
            "stop": 1778513561600,
            "duration": 50,
            "statusDetails": {
              "message": "Status: passed | Duration: ~100ms"
            }
          }
        ]
      },
      {
        "name": "📌 Update profile info",
        "status": "passed",
        "start": 1779082382383,
        "stop": 1779082382483,
        "duration": 100,
        "steps": []
      }
    ],
    "attachments": [],
    "extra": {
      "selenium": {
        "retries": 0,
        "browser": {
          "name": "chrome",
          "version": "120.0",
          "platform": "Windows 10"
        }
      },
      "parameters": [],
      "testClass": "com.example.selenium.tests.DemoTests",
      "testMethod": "User Profile Test"
    }
  },
  {
    "uuid": "dd338ea3-4a1e-4c43-b456-e26851df78ac",
    "tool": "selenium",
    "name": "Navigation Menu Test",
    "fullName": "com.example.selenium.tests.DemoTests.Navigation Menu Test",
    "status": "passed",
    "stage": "finished",
    "start": 1779082385883,
    "stop": 1779082388883,
    "duration": 3000,
    "steps": [],
    "attachments": [],
    "extra": {
      "selenium": {
        "retries": 0,
        "browser": {
          "name": "chrome",
          "version": "120.0",
          "platform": "Windows 10"
        }
      },
      "parameters": [],
      "testClass": "com.example.selenium.tests.DemoTests",
      "testMethod": "Navigation Menu Test"
    }
  },
  {
    "uuid": "ff4939bc-10e3-45bb-9228-bc4c4c9d2104",
    "tool": "selenium",
    "name": "Filter Products Test",
    "fullName": "com.example.selenium.tests.DemoTests.Filter Products Test",
    "status": "passed",
    "stage": "finished",
    "start": 1779082388883,
    "stop": 1779082392883,
    "duration": 4000,
    "steps": [
      {
        "name": "📌 Apply filters",
        "status": "passed",
        "start": 1779082388883,
        "stop": 1779082388983,
        "duration": 100,
        "steps": []
      },
      {
        "name": "📌 Verify filtered results",
        "status": "passed",
        "start": 1779082390383,
        "stop": 1779082390483,
        "duration": 100,
        "steps": []
      }
    ],
    "attachments": [],
    "extra": {
      "selenium": {
        "retries": 0,
        "browser": {
          "name": "chrome",
          "version": "120.0",
          "platform": "Windows 10"
        }
      },
      "parameters": [],
      "testClass": "com.example.selenium.tests.DemoTests",
      "testMethod": "Filter Products Test"
    }
  },
  {
    "uuid": "84c4f58d-e4f1-4dbf-93a7-6578d4c695e2",
    "tool": "selenium",
    "name": "Sort Products Test",
    "fullName": "com.example.selenium.tests.DemoTests.Sort Products Test",
    "status": "passed",
    "stage": "finished",
    "start": 1779082392883,
    "stop": 1779082396383,
    "duration": 3500,
    "steps": [],
    "attachments": [],
    "extra": {
      "selenium": {
        "retries": 0,
        "browser": {
          "name": "chrome",
          "version": "120.0",
          "platform": "Windows 10"
        }
      },
      "parameters": [],
      "testClass": "com.example.selenium.tests.DemoTests",
      "testMethod": "Sort Products Test"
    }
  },
  {
    "uuid": "cb8e083e-6a81-483b-b5cb-e3f85a9e2edf",
    "tool": "selenium",
    "name": "Product Details Test",
    "fullName": "com.example.selenium.tests.DemoTests.Product Details Test",
    "status": "skipped",
    "stage": "finished",
    "start": 1779082396383,
    "stop": 1779082396383,
    "duration": 0,
    "steps": [],
    "attachments": [],
    "extra": {
      "selenium": {
        "retries": 0,
        "browser": {
          "name": "chrome",
          "version": "120.0",
          "platform": "Windows 10"
        }
      },
      "parameters": [],
      "testClass": "com.example.selenium.tests.DemoTests",
      "testMethod": "Product Details Test"
    }
  },
  {
    "uuid": "e3c701e3-f21f-4723-9b38-8e6e7cf14abd",
    "tool": "selenium",
    "name": "Wishlist Test",
    "fullName": "com.example.selenium.tests.DemoTests.Wishlist Test",
    "status": "passed",
    "stage": "finished",
    "start": 1779082396383,
    "stop": 1779082400583,
    "duration": 4200,
    "steps": [],
    "attachments": [],
    "extra": {
      "selenium": {
        "retries": 0,
        "browser": {
          "name": "chrome",
          "version": "120.0",
          "platform": "Windows 10"
        }
      },
      "parameters": [],
      "testClass": "com.example.selenium.tests.DemoTests",
      "testMethod": "Wishlist Test"
    }
  }
]